aqworker/__init__.py
aqworker/cli/__init__.py
aqworker/cli/cli.py
aqworker/cli/commands.py
aqworker/cli/loader.py
aqworker/constants.py
aqworker/core.py
aqworker/handler/__init__.py
aqworker/handler/base.py
aqworker/handler/registry.py
aqworker/job/__init__.py
aqworker/job/base.py
aqworker/job/models.py
aqworker/job/queue.py
aqworker/job/scheduler.py
aqworker/job/service.py
aqworker/logger.py
aqworker/worker/__init__.py
aqworker/worker/base.py
aqworker/worker/dispatcher.py
aqworker/worker/registry.py
aqworker-0.1.7.dist-info/WHEEL
aqworker-0.1.7.dist-info/entry_points.txt
aqworker-0.1.7.dist-info/METADATA
aqworker-0.1.7.dist-info/RECORD
