Metadata-Version: 2.3
Name: aqworker
Version: 0.1.7
Summary: Async Redis-backed job runner for Python apps. AQWorker orchestrates workers, handlers, and queues with auto-discovery, retries, CLI tooling, and FastAPI-friendly async processing while staying framework agnostic.
Keywords: 
Author: Do Quoc Vuong
Author-email: Do Quoc Vuong <vuongtlt13@gmail.com>
Classifier: Programming Language :: Python :: 3
Classifier: License :: OSI Approved :: MIT License
Classifier: Operating System :: OS Independent
Requires-Dist: pydantic>=2.12.4
Requires-Dist: redis>=7.1.0
Requires-Dist: typer>=0.20.0
Requires-Dist: croniter>=2.0.0
Requires-Python: >=3.10, <4.0
Project-URL: Homepage, https://github.com/vuongtlt13/aqworker
Project-URL: Issues, https://github.com/vuongtlt13/aqworker/issues
Project-URL: License, https://opensource.org/licenses/MIT
